{"player1":{"RewardDanceOverlord":0,"RewardDanceStalker":0,"RewardDanceGhost":0,"RewardDanceColossus":0,"RewardDanceRoach":0,"RewardDanceOracle":0,"RewardDanceMule":0,"RewardDanceViking":0,"RewardDanceInfestor":0,"GameHeartActive":0,"SprayProtoss":20504,"WarpGateResearch":5627,"Charge":9827,"ProtossGroundWeaponsLevel1":10581,"PsiStormTech":11905,"ProtossGroundWeaponsLevel2":14351,"BlinkTech":14378,"PhoenixRangeUpgrade":14656,"ProtossAirWeaponsLevel1":14832,"ProtossGroundWeaponsLevel3":18166,"ProtossAirWeaponsLevel2":20807,"ProtossShieldsLevel1":20821},"player2":{"RewardDanceOverlord":0,"RewardDanceStalker":0,"RewardDanceGhost":0,"RewardDanceColossus":0,"RewardDanceRoach":0,"RewardDanceOracle":0,"RewardDanceMule":0,"RewardDanceViking":0,"RewardDanceInfestor":0,"GameHeartActive":0,"SprayZerg":15161,"zerglingmovementspeed":5843,"GlialReconstitution":9779,"ZergMeleeWeaponsLevel1":10237,"CentrificalHooks":12080,"ZergFlyerWeaponsLevel1":12183,"ZergMeleeWeaponsLevel2":13325,"ZergMissileWeaponsLevel1":17361,"ZergMeleeWeaponsLevel3":20880}}